cartel/__init__.py
cartel/cartel.py
cartel/new_cartel_text.py
cartel-1.1.dist-info/METADATA
cartel-1.1.dist-info/WHEEL
cartel-1.1.dist-info/top_level.txt
cartel-1.1.dist-info/RECORD
