Metadata-Version: 2.4
Name: cartel
Version: 1.1
Summary: Библиотека cartel: как ей пользоваться
Author-email: mistertayodimon <dimondimonych1@outlook.com>
License: MIT License
Requires-Dist: colorama
